DesignWorkshop/sequential/sequential.v
module clockgen(clk);
output clk;
parameter period = 10;
parameter initial_value = 1'b0;
reg clk;
initial
begin
	clk = initial_value;
	forever #(period/2) clk = ~clk;
end
endmodule

module flipflop(clk, rst, d, q);
input clk, rst, d;
output q;
reg q;
always @(posedge rst or posedge clk)
	if (rst)
		q <= 1'b0;
	else
		q <= d;
endmodule

module flipflopb(clk, rst, d, q);
input clk, rst, d;
output q;
reg q;
always @(posedge rst or posedge clk)
	if (rst)
		q = 1'b0;
	else
		q = d;
endmodule

module latch(en, rst, d, q);
input en, rst, d;
output q;
reg q;
always @(rst or en or d)
	if (rst)
		q <= 1'b0;
	else if (en)
		q <= d;
endmodule

module tb;
wire fclk, clk;
reg rst, d;
wire qf, qfc, ql;

clockgen #(10) fclkgen(fclk);
clockgen #(20) clkgen(clk);

flipflop ff(clk, rst, d, qf);
flipflop ffc(clk, rst, qf, qfc);

latch l(clk, rst, d, ql);

initial
begin
	rst = 1'b0;
	d = 1'b0;
	#5 rst = 1'b1;
	#10 rst = 1'b0;
	@(negedge fclk) d = 1'b1;
	@(negedge fclk);
	@(posedge fclk) d = ~d;
	@(negedge fclk);
	@(negedge fclk);
	@(posedge fclk) d = ~d;
	@(negedge fclk);
	@(posedge fclk) d = ~d;
end
initial
begin
	$dumpvars;
	#200 $finish;
end
endmodule

DesignWorkshop/sequential/dump.vcd
$date
	Sat Mar 23 10:17:19 2024
$end
$version
	Icarus Verilog
$end
$timescale
	1s
$end
$scope module flipflopb $end
$var wire 1 ! clk $end
$var wire 1 " d $end
$var wire 1 # rst $end
$var reg 1 $ q $end
$upscope $end
$scope module tb $end
$var wire 1 % ql $end
$var wire 1 & qfc $end
$var wire 1 ' qf $end
$var wire 1 ( fclk $end
$var wire 1 ) clk $end
$var reg 1 * d $end
$var reg 1 + rst $end
$scope module clkgen $end
$var reg 1 ) clk $end
$upscope $end
$scope module fclkgen $end
$var reg 1 ( clk $end
$upscope $end
$scope module ff $end
$var wire 1 ) clk $end
$var wire 1 * d $end
$var wire 1 + rst $end
$var reg 1 ' q $end
$upscope $end
$scope module ffc $end
$var wire 1 ) clk $end
$var wire 1 ' d $end
$var wire 1 + rst $end
$var reg 1 & q $end
$upscope $end
$scope module l $end
$var wire 1 * d $end
$var wire 1 ) en $end
$var wire 1 + rst $end
$var reg 1 % q $end
$upscope $end
$upscope $end
$enddefinitions $end
#0
$dumpvars
0+
0*
0)
0(
x'
x&
x%
x$
z#
z"
z!
$end
#5
0'
0&
0%
1+
1(
#10
0(
1)
#15
1(
0+
#20
1*
0(
0)
#25
1(
#30
1'
1%
0(
1)
#35
0%
0*
1(
#40
0(
0)
#45
1(
#50
1&
0'
0(
1)
#55
1%
1*
1(
#60
0(
0)
#65
0*
1(
#70
0&
0%
0(
1)
